README
setup.py
django_revcanonical.egg-info/PKG-INFO
django_revcanonical.egg-info/SOURCES.txt
django_revcanonical.egg-info/dependency_links.txt
django_revcanonical.egg-info/top_level.txt
revcanonical/__init__.py
revcanonical/baseconv.py
revcanonical/urls.py
revcanonical/utils.py
revcanonical/views.py
revcanonical/templatetags/__init__.py
revcanonical/templatetags/revcanontags.py