Metadata-Version: 1.0
Name: django-revcanonical
Version: 1.0
Summary: An implementation of rev=canonical url shortening for Django.
Home-page: http://hg.piranha.org.ua/django-revcanonical/
Author: Alexander Solovyov
Author-email: piranha@piranha.org.ua
License: BSD
Platform: UNKNOWN
Classifier: Development Status :: 4 - Beta
Classifier: Framework :: Django
Classifier: Intended Audience :: Developers
Classifier: License :: OSI Approved :: BSD License
Classifier: Operating System :: OS Independent
Classifier: Programming Language :: Python
Classifier: Topic :: Internet :: WWW/HTTP
